pushsafer.py
python_pushsafer-1.2.dist-info/AUTHORS.rst
python_pushsafer-1.2.dist-info/LICENSE
python_pushsafer-1.2.dist-info/METADATA
python_pushsafer-1.2.dist-info/WHEEL
python_pushsafer-1.2.dist-info/top_level.txt
python_pushsafer-1.2.dist-info/RECORD
