Metadata-Version: 2.1
Name: python-pushsafer
Version: 1.2
Summary: Comprehensive bindings for the Pushsafer.com notification service
Home-page: https://github.com/appzer/python-pushsafer
Author: Kevin Siml
Author-email: info@appzer.de
License: GNU GPLv3
Platform: UNKNOWN
License-File: LICENSE
License-File: AUTHORS.rst
Requires-Dist: requests (>=1.0)
